README.md
setup.py
onecat_task_queue/__init__.py
onecat_task_queue/priority.py
onecat_task_queue/queue.py
onecat_task_queue/redirect.py
onecat_task_queue/task.py
onecat_task_queue.egg-info/PKG-INFO
onecat_task_queue.egg-info/SOURCES.txt
onecat_task_queue.egg-info/dependency_links.txt
onecat_task_queue.egg-info/top_level.txt
onecat_task_queue_test/__init__.py
onecat_task_queue_test/example.py