Metadata-Version: 2.1
Name: onecat-task-queue
Version: 1.0.1
Summary: 简单异步任务队列。版本[1.0.1] 更新内容：又是造轮子系列咯，Python上有很多成熟完善的异步任务队列框架可以用，比如Celery，或者RQ，不过这些都不自带消息队列服务，都需要使用Redis、RabbitMQ之类的消息队列才行，我用到小项目中又不需要附带这么多东西，于是自己动手来实现咯。
Home-page: https://gitee.com/deali/OneCat-TaskQueue
Author: DealiAxy
Author-email: dealiaxy@gmail.com
License: UNKNOWN
Platform: UNKNOWN
Classifier: Programming Language :: Python :: 3.6
Classifier: License :: OSI Approved :: GNU General Public License v3 (GPLv3)
Classifier: Operating System :: OS Independent
